utilicity/__init__.py
utilicity/_types.py
utilicity/fluent.py
utilicity/helpers.py
utilicity/items/__init__.py
utilicity/items/dicts.py
utilicity/items/helpers.py
utilicity/iterators.py
utilicity/sentinels.py
utilicity/strings.py
utilicity/traversing.py
utilicity/vars.py
utilicity-0.2.2.dist-info/WHEEL
utilicity-0.2.2.dist-info/METADATA
utilicity-0.2.2.dist-info/RECORD
